{
  "elements": ["metal", "wood", "water", "fire", "earth"],
  "elementMatrix": {
    "metal": { "wood": 1.25, "fire": 0.85, "water": 1.1, "earth": 0.95 },
    "wood": { "earth": 1.25, "metal": 0.85, "fire": 1.1, "water": 0.95 },
    "water": { "fire": 1.25, "earth": 0.85, "wood": 1.1, "metal": 0.95 },
    "fire": { "metal": 1.25, "water": 0.85, "earth": 1.1, "wood": 0.95 },
    "earth": { "water": 1.25, "wood": 0.85, "metal": 1.1, "fire": 0.95 }
  },
  "characters": [
    { "id": "qiuniu", "name": "囚牛", "element": "random", "atk": 100, "agi": 95, "dodge": 0.12, "def": 90, "crit": 0.1, "critDmg": 1.5 },
    { "id": "yazi", "name": "睚眦", "element": "random", "atk": 115, "agi": 95, "dodge": 0.08, "def": 75, "crit": 0.14, "critDmg": 1.6 }
  ],
  "fruits": [
    { "element": "metal", "selfAtkFlat": 8, "other": { "critRatePct": 0.02, "max": 0.12 } },
    { "element": "wood", "selfAtkFlat": 8, "other": { "agiFlat": 5, "max": 40 } },
    { "element": "water", "selfAtkFlat": 8, "other": { "dodgePct": 0.02, "max": 0.12 } },
    { "element": "fire", "selfAtkFlat": 8, "other": { "critDmg": 0.1, "max": 0.6 } },
    { "element": "earth", "selfAtkFlat": 8, "other": { "defFlat": 8, "max": 64 } }
  ],
  "items": [
    { "id": "invuln", "name": "金钟罩", "duration": 5, "cooldown": 90, "type": "invulnerable", "trigger": "onUse" },
    { "id": "boots", "name": "神行鞋", "duration": 6, "cooldown": 90, "type": "speed", "multiplier": 2, "trigger": "onUse" },
    { "id": "potion", "name": "疗愈丹", "type": "heal", "healAmount": 40, "cooldown": 30, "trigger": "onUse" }
  ],
  "balance": {
    "tickRate": 20,
    "baseMove": 5,
    "agiMoveCoef": 0.02,
    "agiAspdCoef": 0.003,
    "agiCastCoef": 0.001,
    "aspdCap": 1.3,
    "castCap": 0.15,
    "kDef": 100,
    "zoneBuffAtkPct": 0.05,
    "zoneDebuffDefPct": 0.05,
    "stormDpsPct": [0.05, 0.07, 0.09, 0.11, 0.13],
    "ringShrinkTimes": [180, 270, 360, 450, 540],
    "ringShrinkFactor": 0.8,
    "sameFruitAtkCap": 64,
    "sameFruitDiminishStart": 5,
    "sameFruitDiminishRate": 0.7,
    "mobSpawnEvery": 20,
    "itemDropChance": 0.1,
    "baseHit": 0.9,
    "agiHitCoef": 0.0015,
    "minHit": 0.4,
    "maxHit": 1.0,
    "attackCooldownMs": 600,
    "slotCount": 3
  }
}